flasking/__init__.py
flasking-0.0.0.dist-info/METADATA
flasking-0.0.0.dist-info/WHEEL
flasking-0.0.0.dist-info/RECORD
